GeiMeiziJiangPythonDiyiji/README.md
GeiMeiziJiangPythonDiyiji/__init__.py
GeiMeiziJiangPythonDiyiji/__main__.py
GeiMeiziJiangPythonDiyiji/file.epub
GeiMeiziJiangPythonDiyiji/index.html
GeiMeiziJiangPythonDiyiji/css/__init__.py
GeiMeiziJiangPythonDiyiji/css/annotations.css
GeiMeiziJiangPythonDiyiji/css/main.css
GeiMeiziJiangPythonDiyiji/css/normalize.css
GeiMeiziJiangPythonDiyiji/css/popup.css
GeiMeiziJiangPythonDiyiji/font/__init__.py
GeiMeiziJiangPythonDiyiji/font/fontello.eot
GeiMeiziJiangPythonDiyiji/font/fontello.svg
GeiMeiziJiangPythonDiyiji/font/fontello.ttf
GeiMeiziJiangPythonDiyiji/font/fontello.woff
GeiMeiziJiangPythonDiyiji/img/__init__.py
GeiMeiziJiangPythonDiyiji/img/annotator-glyph-sprite.png
GeiMeiziJiangPythonDiyiji/img/annotator-icon-sprite.png
GeiMeiziJiangPythonDiyiji/img/apple-touch-icon.png
GeiMeiziJiangPythonDiyiji/img/cancelfullscreen.png
GeiMeiziJiangPythonDiyiji/img/close.png
GeiMeiziJiangPythonDiyiji/img/fullscreen.png
GeiMeiziJiangPythonDiyiji/img/loader.gif
GeiMeiziJiangPythonDiyiji/img/menu-icon.png
GeiMeiziJiangPythonDiyiji/img/save.png
GeiMeiziJiangPythonDiyiji/img/saved.png
GeiMeiziJiangPythonDiyiji/img/settings-s.png
GeiMeiziJiangPythonDiyiji/img/settings.png
GeiMeiziJiangPythonDiyiji/img/star.png
GeiMeiziJiangPythonDiyiji/js/__init__.py
GeiMeiziJiangPythonDiyiji/js/epub.js
GeiMeiziJiangPythonDiyiji/js/epub.min.js
GeiMeiziJiangPythonDiyiji/js/epub.min.map
GeiMeiziJiangPythonDiyiji/js/hooks.min.js
GeiMeiziJiangPythonDiyiji/js/hooks.min.map
GeiMeiziJiangPythonDiyiji/js/reader.js
GeiMeiziJiangPythonDiyiji/js/reader.js.map
GeiMeiziJiangPythonDiyiji/js/reader.min.js
GeiMeiziJiangPythonDiyiji/js/reader.min.map
GeiMeiziJiangPythonDiyiji/js/hooks/__init__.py
GeiMeiziJiangPythonDiyiji/js/hooks/extensions/__init__.py
GeiMeiziJiangPythonDiyiji/js/hooks/extensions/highlight.js
GeiMeiziJiangPythonDiyiji/js/libs/__init__.py
GeiMeiziJiangPythonDiyiji/js/libs/jquery.min.js
GeiMeiziJiangPythonDiyiji/js/libs/localforage.min.js
gei_meizi_jiang_python_diyiji-2024.3.3.0.dist-info/METADATA
gei_meizi_jiang_python_diyiji-2024.3.3.0.dist-info/WHEEL
gei_meizi_jiang_python_diyiji-2024.3.3.0.dist-info/entry_points.txt
gei_meizi_jiang_python_diyiji-2024.3.3.0.dist-info/top_level.txt
gei_meizi_jiang_python_diyiji-2024.3.3.0.dist-info/RECORD
